palett/__init__.py
palett/cards/__init__.py
palett/cards/amber.py
palett/cards/blue.py
palett/cards/blue_grey.py
palett/cards/brown.py
palett/cards/cyan.py
palett/cards/deep_orange.py
palett/cards/deep_purple.py
palett/cards/green.py
palett/cards/grey.py
palett/cards/indigo.py
palett/cards/light_blue.py
palett/cards/light_green.py
palett/cards/lime.py
palett/cards/orange.py
palett/cards/pink.py
palett/cards/purple.py
palett/cards/red.py
palett/cards/teal.py
palett/cards/yellow.py
palett/convert/__init__.py
palett/convert/hex_hsl.py
palett/convert/hex_int.py
palett/convert/hex_rgb.py
palett/convert/hsl_hex.py
palett/convert/hsl_rgb.py
palett/convert/rgb_hex.py
palett/convert/rgb_hsl.py
palett/convert/rgb_int.py
palett/convert/utils/__init__.py
palett/convert/utils/hex/__init__.py
palett/convert/utils/hex/dilute_hex.py
palett/convert/utils/hsl/__init__.py
palett/convert/utils/hsl/hf.py
palett/convert/utils/rgb/__init__.py
palett/convert/utils/rgb/bound.py
palett/convert/utils/rgb/hue.py
palett/dye/__init__.py
palett/dye/color_to_ansi/__init__.py
palett/dye/dye_factory/__init__.py
palett/dye/hex/__init__.py
palett/dye/hex/dyer.py
palett/dye/hex/hex_ansi.py
palett/dye/hex/prep_dyer.py
palett/dye/rgb/__init__.py
palett/dye/rgb/dyer.py
palett/dye/rgb/prep_dyer.py
palett/dye/rgb/rgb_ansi.py
palett/dye/utils/__init__.py
palett/dye/utils/br.py
palett/dye/utils/parse_effects.py
palett/enum/__init__.py
palett/enum/color_cards/__init__.py
palett/enum/color_degrees/__init__.py
palett/enum/color_groups/__init__.py
palett/enum/color_spaces/__init__.py
palett/enum/font_effects/__init__.py
palett/flopper/__init__.py
palett/flopper/palett_flopper/__init__.py
palett/fluo/__init__.py
palett/fluo/fluo_entries/__init__.py
palett/fluo/fluo_matrix/__init__.py
palett/fluo/fluo_matrix/fluo_columnwise.py
palett/fluo/fluo_matrix/fluo_pointwise.py
palett/fluo/fluo_matrix/fluo_rowwise.py
palett/fluo/fluo_vector/__init__.py
palett/presets/__init__.py
palett/presets/aqua.py
palett-0.0.18.dist-info/WHEEL
palett-0.0.18.dist-info/METADATA
palett-0.0.18.dist-info/RECORD
